maphash/__init__.py
maphash/py.typed
maphash-0.1.2.dist-info/LICENSE
maphash-0.1.2.dist-info/METADATA
maphash-0.1.2.dist-info/WHEEL
maphash-0.1.2.dist-info/RECORD
