Metadata-Version: 2.1
Name: maphash
Version: 0.1.2
Summary: 
Author: Jakob Klepp
Author-email: jakob.klepp@moonvision.io
Requires-Python: >=3.8,<4
Classifier: Programming Language :: Python :: 3
Classifier: Programming Language :: Python :: 3.8
Classifier: Programming Language :: Python :: 3.9
Classifier: Programming Language :: Python :: 3.10
Classifier: Programming Language :: Python :: 3.11
Classifier: Programming Language :: Python :: 3.12
